README
setup.py
yolk/__init__.py
yolk/cli.py
yolk/metadata.py
yolk/pypi.py
yolk/setuptools_support.py
yolk/utils.py
yolk/yolklib.py
yolk.egg-info/PKG-INFO
yolk.egg-info/SOURCES.txt
yolk.egg-info/dependency_links.txt
yolk.egg-info/entry_points.txt
yolk.egg-info/requires.txt
yolk.egg-info/top_level.txt
yolk/plugins/__init__.py
yolk/plugins/base.py