Metadata-Version: 1.0
Name: yolk
Version: 0.4.2
Summary: Command-line tool for querying PyPI and Python packages installed on your system.
Home-page: https://github.com/cakebread/yolk
Author: Rob Cakebread
Author-email: cakebread @ gmail
License: BSD License
Keywords: PyPI setuptools cheeseshop distutils eggs package management
Platform: UNKNOWN
Classifier: Development Status :: 4 - Beta
Classifier: Intended Audience :: Developers
Classifier: License :: OSI Approved :: BSD License
Classifier: Programming Language :: Python
Classifier: Topic :: Software Development :: Libraries :: Python Modules
